<?xml version="1.0" encoding="UTF-8"?>
<objects serializationModel="Studio.02.01.00">
	<object class="AudioFile" id="{b292534b-af2e-4328-bc6d-7705d9b7bce2}">
		<property name="assetPath">
			<value>Clocks, Tick, Electric, Tick 01 SND12582 1.wav</value>
		</property>
		<property name="frequencyInKHz">
			<value>96</value>
		</property>
		<property name="channelCount">
			<value>1</value>
		</property>
		<property name="length">
			<value>0.097000000000000003</value>
		</property>
		<relationship name="masterAssetFolder">
			<destination>{df5639b5-3808-4165-baef-b6a196a82941}</destination>
		</relationship>
	</object>
</objects>
